connectors/__init__.py
connectors/http_api/GPT_schema.yml
connectors/http_api/TEST_AUTH.md
connectors/http_api/__init__.py
connectors/http_api/add_user.py
connectors/http_api/app.py
connectors/http_api/auth.py
connectors/http_api/schemas.py
connectors/http_api/streamlit_auth.py
connectors/mcp_server/README.md
connectors/mcp_server/__init__.py
connectors/mcp_server/server.py
nancy_brain/__init__.py
nancy_brain/_build_info.py
nancy_brain/admin_ui.py
nancy_brain/chunking.py
nancy_brain/cli.py
nancy_brain/config_validation.py
nancy_brain/summarization.py
nancy_brain/utils_weights.py
nancy_brain/weights_persistence.py
rag_core/__init__.py
rag_core/registry.py
rag_core/search.py
rag_core/service.py
rag_core/store.py
rag_core/types.py
scripts/build_knowledge_base.py
scripts/manage_articles.py
scripts/manage_pdf_articles.py
scripts/manage_repositories.py
scripts/pdf_utils.py
scripts/text_extract.py
nancy_brain-0.2.0.dist-info/METADATA
nancy_brain-0.2.0.dist-info/WHEEL
nancy_brain-0.2.0.dist-info/entry_points.txt
nancy_brain-0.2.0.dist-info/licenses/LICENSE
nancy_brain-0.2.0.dist-info/RECORD
