Metadata-Version: 2.4
Name: nancy-brain
Version: 0.2.0
Summary: Turn any GitHub repository into a searchable knowledge base for AI agents
Project-URL: Homepage, https://github.com/AmberLee2427/nancy-brain
Project-URL: Documentation, https://github.com/AmberLee2427/nancy-brain/blob/main/README.md
Project-URL: Repository, https://github.com/AmberLee2427/nancy-brain
Project-URL: Issues, https://github.com/AmberLee2427/nancy-brain/issues
Author-email: Amber Malpas <malpas.1@osu.edu>
License: MIT
License-File: LICENSE
Keywords: AI,RAG,embeddings,github,knowledge-base,research,search
Classifier: Development Status :: 4 - Beta
Classifier: Environment :: Console
Classifier: Environment :: Web Environment
Classifier: Intended Audience :: Developers
Classifier: Intended Audience :: Science/Research
Classifier: License :: OSI Approved :: MIT License
Classifier: Operating System :: OS Independent
Classifier: Programming Language :: Python :: 3
Classifier: Programming Language :: Python :: 3.10
Classifier: Programming Language :: Python :: 3.11
Classifier: Programming Language :: Python :: 3.12
Classifier: Topic :: Scientific/Engineering :: Artificial Intelligence
Classifier: Topic :: Scientific/Engineering :: Information Analysis
Classifier: Topic :: Software Development :: Libraries :: Python Modules
Classifier: Topic :: Text Processing :: Indexing
Requires-Python: >=3.10
Requires-Dist: aiohttp>=3.8.0
Requires-Dist: anthropic
Requires-Dist: astropy>=4.2
Requires-Dist: chunky-files[tree]>=1.0.0
Requires-Dist: click>=8.0.0
Requires-Dist: docutils>=0.20
Requires-Dist: faiss-cpu>=1.7.1.post2
Requires-Dist: fastapi>=0.110.0
Requires-Dist: mcp>=1.13.0
Requires-Dist: nb4llm>=0.1.3
Requires-Dist: passlib[bcrypt]>=1.7.4
Requires-Dist: pydantic>=2.0.0
Requires-Dist: pylatexenc>=2.10
Requires-Dist: python-dotenv
Requires-Dist: python-dotenv>=1.0.0
Requires-Dist: python-jose>=3.3.0
Requires-Dist: pyyaml>=5.3
Requires-Dist: regex>=2022.8.17
Requires-Dist: requests>=2.28.0
Requires-Dist: slack-bolt>=1.18.0
Requires-Dist: slack-sdk>=3.18.0
Requires-Dist: streamlit>=1.28.0
Requires-Dist: torch>=1.12.1
Requires-Dist: transformers>=4.45.0
Requires-Dist: txtai>=7.0.0
Requires-Dist: uvicorn>=0.29.0
Requires-Dist: zstandard
Provides-Extra: dev
Requires-Dist: black>=25.1.0; extra == 'dev'
Requires-Dist: build>=0.10.0; extra == 'dev'
Requires-Dist: bump-my-version>=0.11.0; extra == 'dev'
Requires-Dist: coverage>=7.0.0; extra == 'dev'
Requires-Dist: flake8>=7.3.0; extra == 'dev'
Requires-Dist: hatch; extra == 'dev'
Requires-Dist: ipykernel; extra == 'dev'
Requires-Dist: ipywidgets; extra == 'dev'
Requires-Dist: jupyter; extra == 'dev'
Requires-Dist: pre-commit>=3.0.0; extra == 'dev'
Requires-Dist: pytest-asyncio>=0.21.0; extra == 'dev'
Requires-Dist: pytest-cov>=4.0.0; extra == 'dev'
Requires-Dist: pytest>=7.0.0; extra == 'dev'
Requires-Dist: rich>=13.0.0; extra == 'dev'
Requires-Dist: twine>=4.0.0; extra == 'dev'
Provides-Extra: docs
Requires-Dist: mkdocs-autorefs>=0.4.1; extra == 'docs'
Requires-Dist: mkdocs-click>=0.8.0; extra == 'docs'
Requires-Dist: mkdocs-material>=9.0.0; extra == 'docs'
Requires-Dist: mkdocstrings[python]>=0.20.0; extra == 'docs'
Provides-Extra: pdf
Requires-Dist: pdfplumber; extra == 'pdf'
Requires-Dist: pymupdf; extra == 'pdf'
Requires-Dist: pypdf2; extra == 'pdf'
Requires-Dist: tika>=2.6.0; extra == 'pdf'
